multiprocshapefinder/README.MD
multiprocshapefinder/__init__.py
multiprocshapefinder/multishapemain.py
multiprocshapefinder/requirements.txt
multiprocshapefinder/thirdparty.json
multiprocshapefinder-0.12.dist-info/LICENSE.rst
multiprocshapefinder-0.12.dist-info/METADATA
multiprocshapefinder-0.12.dist-info/WHEEL
multiprocshapefinder-0.12.dist-info/top_level.txt
multiprocshapefinder-0.12.dist-info/RECORD
