Metadata-Version: 2.1
Name: multiprocshapefinder
Version: 0.12
Summary: detects and analyzes shapes in images using parallel processing.
Home-page: https://github.com/hansalemaos/multiprocshapefinder
Author: Johannes Fischer
Author-email: aulasparticularesdealemaosp@gmail.com
License: MIT
Keywords: multiprocessing,shape,matching,finder
Classifier: Development Status :: 4 - Beta
Classifier: Programming Language :: Python :: 3 :: Only
Classifier: Programming Language :: Python :: 3.10
Classifier: Topic :: Software Development :: Libraries :: Python Modules
Classifier: Topic :: Utilities
License-File: LICENSE.rst
Requires-Dist: a-cv-imwrite-imread-plus
Requires-Dist: a-pandas-ex-apply-ignore-exceptions
Requires-Dist: flatten-everything
Requires-Dist: more-itertools
Requires-Dist: multiprocca
Requires-Dist: numexpr
Requires-Dist: numpy
Requires-Dist: opencv-python
Requires-Dist: pandas
